uonet_request_signer_hebe/__init__.py
uonet_request_signer_hebe/signer.py
uonet_request_signer_hebe-0.1.1.dist-info/LICENSE
uonet_request_signer_hebe-0.1.1.dist-info/METADATA
uonet_request_signer_hebe-0.1.1.dist-info/WHEEL
uonet_request_signer_hebe-0.1.1.dist-info/top_level.txt
uonet_request_signer_hebe-0.1.1.dist-info/RECORD
