Metadata-Version: 2.1
Name: uonet-request-signer-hebe
Version: 0.1.1
Summary: UONET+ (hebe) request signer for Python
Home-page: https://github.com/wulkanowy/uonet-request-signer
Author: Wulkanowy
Author-email: wulkanowyinc@gmail.com
Maintainer: Kuba Szczodrzyński
Maintainer-email: kuba@szczodrzynski.pl
License: MIT
Platform: UNKNOWN
Classifier: Development Status :: 4 - Beta
Classifier: Intended Audience :: Developers
Classifier: License :: OSI Approved :: MIT License
Classifier: Natural Language :: English
Classifier: Operating System :: OS Independent
Classifier: Programming Language :: Python :: 3.5
Classifier: Programming Language :: Python :: 3.6
Classifier: Programming Language :: Python :: 3.7
Classifier: Programming Language :: Python :: 3.8
Classifier: Topic :: Education
Classifier: Topic :: Internet :: WWW/HTTP
Classifier: Topic :: Security :: Cryptography
Classifier: Topic :: Software Development :: Libraries :: Python Modules
Requires-Dist: pyopenssl
Provides-Extra: testing
Requires-Dist: pytest ; extra == 'testing'
